zwsp_linker/__init__.py
zwsp_linker-2025.9.1498.dist-info/licenses/LICENSE
zwsp_linker-2025.9.1498.dist-info/METADATA
zwsp_linker-2025.9.1498.dist-info/WHEEL
zwsp_linker-2025.9.1498.dist-info/top_level.txt
zwsp_linker-2025.9.1498.dist-info/RECORD
