Metadata-Version: 2.4
Name: zwsp_linker
Version: 2025.9.1498
Summary: # init.py import re   def safelink_zwsp(text: str) -> str:     """     Insert zero-width spaces into URLs to prevent auto-linking and allow…
Author-email: Eugene Evstafev <hi@eugene.plus>
License: MIT License
Project-URL: Repository, https://pypi.org/project/zwsp_linker/
Requires-Python: >=3.9
License-File: LICENSE
Dynamic: license-file
